refinedoc/__init__.py
refinedoc/enumeration.py
refinedoc/helpers.py
refinedoc/refined_document.py
refinedoc-1.0.1.dist-info/METADATA
refinedoc-1.0.1.dist-info/WHEEL
refinedoc-1.0.1.dist-info/licenses/LICENSE
refinedoc-1.0.1.dist-info/RECORD
